fileprinter/__init__.py
fileprinter/fileprinter.py
fileprinter-0.1.0.dist-info/licenses/LICENSE
fileprinter-0.1.0.dist-info/METADATA
fileprinter-0.1.0.dist-info/WHEEL
fileprinter-0.1.0.dist-info/top_level.txt
fileprinter-0.1.0.dist-info/RECORD
